pywinpty-3.0.1.dist-info/METADATA
pywinpty-3.0.1.dist-info/WHEEL
pywinpty-3.0.1.dist-info/licenses/LICENSE.txt
winpty/OpenConsole.exe
winpty/__init__.py
winpty/conpty.dll
winpty/enums.py
winpty/ptyprocess.py
winpty/tests/__init__.py
winpty/tests/test_pty.py
winpty/tests/test_ptyprocess.py
winpty/winpty-agent.exe
winpty/winpty.cp39-win_amd64.pyd
winpty/winpty.dll
winpty/winpty.pyi
pywinpty-3.0.1.dist-info/RECORD
